{
  "entityType" : "NOTIFICATION_TEMPLATE",
  "entity" : {
    "configuration" : {
      "deliveryMethodsTemplates" : {
        "WEB" : {
          "method" : "WEB",
          "additionalConfig" : {
            "icon" : {
              "enabled" : false
            },
            "actionButtonConfig" : {
              "enabled" : false
            }
          },
          "body" : "Maintenance work is scheduled for tomorrow (7:00 a.m. - 9:00 a.m. UTC)",
          "enabled" : true,
          "subject" : "Infrastructure maintenance"
        }
      }
    },
    "externalId" : null,
    "id" : {
      "entityType" : "NOTIFICATION_TEMPLATE",
      "id" : "a15ef6a0-fab3-11ef-8e77-bd1649368acc"
    },
    "name" : "Maintenance work notification",
    "notificationType" : "GENERAL"
  }
}