{
  "entityType" : "DASHBOARD",
  "entity" : {
    "assignedCustomers" : [ ],
    "configuration" : {
      "description" : "",
      "widgets" : {
        "622ddf4b-0b7a-f19d-6f50-0d6192ace56b" : {
          "typeFullFqn" : "system.line_chart",
          "type" : "timeseries",
          "sizeX" : 8,
          "sizeY" : 5,
          "config" : {
            "datasources" : [ {
              "type" : "entity",
              "name" : "",
              "deviceId" : "46040460-9070-11ef-8b08-b1b78211b00c",
              "entityAliasId" : "0df20127-4849-dab6-fc9d-6201452d51f9",
              "dataKeys" : [ {
                "name" : "Primary Current R",
                "type" : "timeseries",
                "label" : "Primary Current (R)",
                "color" : "#048AD3",
                "settings" : {
                  "yAxisId" : "default",
                  "showInLegend" : true,
                  "dataHiddenByDefault" : false,
                  "type" : "line",
                  "lineSettings" : {
                    "showLine" : true,
                    "step" : false,
                    "stepType" : "start",
                    "smooth" : false,
                    "lineType" : "solid",
                    "lineWidth" : 2,
                    "showPoints" : false,
                    "showPointLabel" : false,
                    "pointLabelPosition" : "top",
                    "pointLabelFont" : {
                      "family" : "Roboto",
                      "size" : 11,
                      "sizeUnit" : "px",
                      "style" : "normal",
                      "weight" : "400",
                      "lineHeight" : "1"
                    },
                    "pointLabelColor" : "rgba(0, 0, 0, 0.76)",
                    "enablePointLabelBackground" : false,
                    "pointLabelBackground" : "rgba(255,255,255,0.56)",
                    "pointShape" : "emptyCircle",
                    "pointSize" : 4,
                    "fillAreaSettings" : {
                      "type" : "none",
                      "opacity" : 0.4,
                      "gradient" : {
                        "start" : 100,
                        "end" : 0
                      }
                    }
                  },
                  "barSettings" : {
                    "showBorder" : false,
                    "borderWidth" : 2,
                    "borderRadius" : 0,
                    "showLabel" : false,
                    "labelPosition" : "top",
                    "labelFont" : {
                      "family" : "Roboto",
                      "size" : 11,
                      "sizeUnit" : "px",
                      "style" : "normal",
                      "weight" : "400",
                      "lineHeight" : "1"
                    },
                    "labelColor" : "rgba(0, 0, 0, 0.76)",
                    "enableLabelBackground" : false,
                    "labelBackground" : "rgba(255,255,255,0.56)",
                    "backgroundSettings" : {
                      "type" : "none",
                      "opacity" : 0.4,
                      "gradient" : {
                        "start" : 100,
                        "end" : 0
                      }
                    }
                  },
                  "comparisonSettings" : {
                    "showValuesForComparison" : false,
                    "comparisonValuesLabel" : "",
                    "color" : ""
                  }
                },
                "_hash" : 0.05320419791431408,
                "units" : "A",
                "decimals" : 2
              }, {
                "name" : "Primary Current Y",
                "type" : "timeseries",
                "label" : "Primary Current (Y)",
                "color" : "#4caf50",
                "settings" : {
                  "yAxisId" : "default",
                  "showInLegend" : true,
                  "dataHiddenByDefault" : false,
                  "type" : "line",
                  "lineSettings" : {
                    "showLine" : true,
                    "step" : false,
                    "stepType" : "start",
                    "smooth" : false,
                    "lineType" : "solid",
                    "lineWidth" : 2,
                    "showPoints" : false,
                    "showPointLabel" : false,
                    "pointLabelPosition" : "top",
                    "pointLabelFont" : {
                      "family" : "Roboto",
                      "size" : 11,
                      "sizeUnit" : "px",
                      "style" : "normal",
                      "weight" : "400",
                      "lineHeight" : "1"
                    },
                    "pointLabelColor" : "rgba(0, 0, 0, 0.76)",
                    "enablePointLabelBackground" : false,
                    "pointLabelBackground" : "rgba(255,255,255,0.56)",
                    "pointShape" : "emptyCircle",
                    "pointSize" : 4,
                    "fillAreaSettings" : {
                      "type" : "none",
                      "opacity" : 0.4,
                      "gradient" : {
                        "start" : 100,
                        "end" : 0
                      }
                    }
                  },
                  "barSettings" : {
                    "showBorder" : false,
                    "borderWidth" : 2,
                    "borderRadius" : 0,
                    "showLabel" : false,
                    "labelPosition" : "top",
                    "labelFont" : {
                      "family" : "Roboto",
                      "size" : 11,
                      "sizeUnit" : "px",
                      "style" : "normal",
                      "weight" : "400",
                      "lineHeight" : "1"
                    },
                    "labelColor" : "rgba(0, 0, 0, 0.76)",
                    "enableLabelBackground" : false,
                    "labelBackground" : "rgba(255,255,255,0.56)",
                    "backgroundSettings" : {
                      "type" : "none",
                      "opacity" : 0.4,
                      "gradient" : {
                        "start" : 100,
                        "end" : 0
                      }
                    }
                  },
                  "comparisonSettings" : {
                    "showValuesForComparison" : false,
                    "comparisonValuesLabel" : "",
                    "color" : ""
                  }
                },
                "_hash" : 0.09429857326897828,
                "decimals" : 2,
                "units" : "A"
              }, {
                "name" : "Primary Current B",
                "type" : "timeseries",
                "label" : "Primary Current (B)",
                "color" : "#f44336",
                "settings" : {
                  "yAxisId" : "default",
                  "showInLegend" : true,
                  "dataHiddenByDefault" : false,
                  "type" : "line",
                  "lineSettings" : {
                    "showLine" : true,
                    "step" : false,
                    "stepType" : "start",
                    "smooth" : false,
                    "lineType" : "solid",
                    "lineWidth" : 2,
                    "showPoints" : false,
                    "showPointLabel" : false,
                    "pointLabelPosition" : "top",
                    "pointLabelFont" : {
                      "family" : "Roboto",
                      "size" : 11,
                      "sizeUnit" : "px",
                      "style" : "normal",
                      "weight" : "400",
                      "lineHeight" : "1"
                    },
                    "pointLabelColor" : "rgba(0, 0, 0, 0.76)",
                    "enablePointLabelBackground" : false,
                    "pointLabelBackground" : "rgba(255,255,255,0.56)",
                    "pointShape" : "emptyCircle",
                    "pointSize" : 4,
                    "fillAreaSettings" : {
                      "type" : "none",
                      "opacity" : 0.4,
                      "gradient" : {
                        "start" : 100,
                        "end" : 0
                      }
                    }
                  },
                  "barSettings" : {
                    "showBorder" : false,
                    "borderWidth" : 2,
                    "borderRadius" : 0,
                    "showLabel" : false,
                    "labelPosition" : "top",
                    "labelFont" : {
                      "family" : "Roboto",
                      "size" : 11,
                      "sizeUnit" : "px",
                      "style" : "normal",
                      "weight" : "400",
                      "lineHeight" : "1"
                    },
                    "labelColor" : "rgba(0, 0, 0, 0.76)",
                    "enableLabelBackground" : false,
                    "labelBackground" : "rgba(255,255,255,0.56)",
                    "backgroundSettings" : {
                      "type" : "none",
                      "opacity" : 0.4,
                      "gradient" : {
                        "start" : 100,
                        "end" : 0
                      }
                    }
                  },
                  "comparisonSettings" : {
                    "showValuesForComparison" : false,
                    "comparisonValuesLabel" : "",
                    "color" : ""
                  }
                },
                "_hash" : 0.14226589454857996,
                "units" : "A",
                "decimals" : 2
              }, {
                "name" : "Primary Current E",
                "type" : "timeseries",
                "label" : "Primary Current (E)",
                "color" : "#ffc107",
                "settings" : {
                  "yAxisId" : "default",
                  "showInLegend" : true,
                  "dataHiddenByDefault" : false,
                  "type" : "line",
                  "lineSettings" : {
                    "showLine" : true,
                    "step" : false,
                    "stepType" : "start",
                    "smooth" : false,
                    "lineType" : "solid",
                    "lineWidth" : 2,
                    "showPoints" : false,
                    "showPointLabel" : false,
                    "pointLabelPosition" : "top",
                    "pointLabelFont" : {
                      "family" : "Roboto",
                      "size" : 11,
                      "sizeUnit" : "px",
                      "style" : "normal",
                      "weight" : "400",
                      "lineHeight" : "1"
                    },
                    "pointLabelColor" : "rgba(0, 0, 0, 0.76)",
                    "enablePointLabelBackground" : false,
                    "pointLabelBackground" : "rgba(255,255,255,0.56)",
                    "pointShape" : "emptyCircle",
                    "pointSize" : 4,
                    "fillAreaSettings" : {
                      "type" : "none",
                      "opacity" : 0.4,
                      "gradient" : {
                        "start" : 100,
                        "end" : 0
                      }
                    }
                  },
                  "barSettings" : {
                    "showBorder" : false,
                    "borderWidth" : 2,
                    "borderRadius" : 0,
                    "showLabel" : false,
                    "labelPosition" : "top",
                    "labelFont" : {
                      "family" : "Roboto",
                      "size" : 11,
                      "sizeUnit" : "px",
                      "style" : "normal",
                      "weight" : "400",
                      "lineHeight" : "1"
                    },
                    "labelColor" : "rgba(0, 0, 0, 0.76)",
                    "enableLabelBackground" : false,
                    "labelBackground" : "rgba(255,255,255,0.56)",
                    "backgroundSettings" : {
                      "type" : "none",
                      "opacity" : 0.4,
                      "gradient" : {
                        "start" : 100,
                        "end" : 0
                      }
                    }
                  },
                  "comparisonSettings" : {
                    "showValuesForComparison" : false,
                    "comparisonValuesLabel" : "",
                    "color" : ""
                  }
                },
                "_hash" : 0.8958501877583913,
                "units" : "A",
                "decimals" : 2
              } ],
              "alarmFilterConfig" : {
                "statusList" : [ "ACTIVE" ]
              },
              "latestDataKeys" : [ ]
            } ],
            "timewindow" : {
              "hideInterval" : false,
              "hideLastInterval" : false,
              "hideQuickInterval" : false,
              "hideAggregation" : false,
              "hideAggInterval" : false,
              "hideTimezone" : false,
              "selectedTab" : 0,
              "realtime" : {
                "realtimeType" : 0,
                "timewindowMs" : 300000,
                "quickInterval" : "CURRENT_HOUR",
                "interval" : 120000
              },
              "aggregation" : {
                "type" : "NONE",
                "limit" : 25000
              },
              "timezone" : null
            },
            "showTitle" : true,
            "backgroundColor" : "rgba(0, 0, 0, 0)",
            "color" : "rgba(0, 0, 0, 0.87)",
            "padding" : "0px",
            "settings" : {
              "comparisonEnabled" : false,
              "timeForComparison" : "previousInterval",
              "comparisonCustomIntervalValue" : 7200000,
              "comparisonXAxis" : {
                "show" : true,
                "label" : "",
                "labelFont" : {
                  "family" : "Roboto",
                  "size" : 12,
                  "sizeUnit" : "px",
                  "style" : "normal",
                  "weight" : "600",
                  "lineHeight" : "1"
                },
                "labelColor" : "rgba(0, 0, 0, 0.54)",
                "position" : "top",
                "showTickLabels" : true,
                "tickLabelFont" : {
                  "family" : "Roboto",
                  "size" : 10,
                  "sizeUnit" : "px",
                  "style" : "normal",
                  "weight" : "400",
                  "lineHeight" : "1"
                },
                "tickLabelColor" : "rgba(0, 0, 0, 0.54)",
                "ticksFormat" : { },
                "showTicks" : true,
                "ticksColor" : "rgba(0, 0, 0, 0.54)",
                "showLine" : true,
                "lineColor" : "rgba(0, 0, 0, 0.54)",
                "showSplitLines" : true,
                "splitLinesColor" : "rgba(0, 0, 0, 0.12)"
              },
              "yAxes" : {
                "default" : {
                  "units" : "A",
                  "decimals" : 2,
                  "show" : true,
                  "label" : "",
                  "labelFont" : {
                    "family" : "Roboto",
                    "size" : 12,
                    "sizeUnit" : "px",
                    "style" : "normal",
                    "weight" : "600",
                    "lineHeight" : "1"
                  },
                  "labelColor" : "rgba(0, 0, 0, 0.54)",
                  "position" : "left",
                  "showTickLabels" : true,
                  "tickLabelFont" : {
                    "family" : "Roboto",
                    "size" : 12,
                    "sizeUnit" : "px",
                    "style" : "normal",
                    "weight" : "400",
                    "lineHeight" : "1"
                  },
                  "tickLabelColor" : "rgba(0, 0, 0, 0.54)",
                  "ticksFormatter" : null,
                  "showTicks" : true,
                  "ticksColor" : "rgba(0, 0, 0, 0.54)",
                  "showLine" : true,
                  "lineColor" : "rgba(0, 0, 0, 0.54)",
                  "showSplitLines" : true,
                  "splitLinesColor" : "rgba(0, 0, 0, 0.12)",
                  "id" : "default",
                  "order" : 0,
                  "min" : 0,
                  "max" : null,
                  "ticksGenerator" : null,
                  "interval" : null,
                  "splitNumber" : null
                }
              },
              "thresholds" : [ ],
              "dataZoom" : true,
              "stack" : false,
              "grid" : {
                "show" : false,
                "backgroundColor" : null,
                "borderWidth" : 1,
                "borderColor" : "#ccc"
              },
              "xAxis" : {
                "show" : true,
                "label" : "",
                "labelFont" : {
                  "family" : "Roboto",
                  "size" : 12,
                  "sizeUnit" : "px",
                  "style" : "normal",
                  "weight" : "600",
                  "lineHeight" : "1"
                },
                "labelColor" : "rgba(0, 0, 0, 0.54)",
                "position" : "bottom",
                "showTickLabels" : true,
                "tickLabelFont" : {
                  "family" : "Roboto",
                  "size" : 10,
                  "sizeUnit" : "px",
                  "style" : "normal",
                  "weight" : "400",
                  "lineHeight" : "1"
                },
                "tickLabelColor" : "rgba(0, 0, 0, 0.54)",
                "ticksFormat" : { },
                "showTicks" : true,
                "ticksColor" : "rgba(0, 0, 0, 0.54)",
                "showLine" : true,
                "lineColor" : "rgba(0, 0, 0, 0.54)",
                "showSplitLines" : true,
                "splitLinesColor" : "rgba(0, 0, 0, 0.12)"
              },
              "noAggregationBarWidthSettings" : {
                "strategy" : "group",
                "groupWidth" : {
                  "relative" : true,
                  "relativeWidth" : 2,
                  "absoluteWidth" : 1000
                },
                "barWidth" : {
                  "relative" : true,
                  "relativeWidth" : 2,
                  "absoluteWidth" : 1000
                }
              },
              "showLegend" : true,
              "legendColumnTitleFont" : {
                "family" : "Roboto",
                "size" : 12,
                "sizeUnit" : "px",
                "style" : "normal",
                "weight" : "400",
                "lineHeight" : "16px"
              },
              "legendColumnTitleColor" : "rgba(0, 0, 0, 0.38)",
              "legendLabelFont" : {
                "family" : "Roboto",
                "size" : 12,
                "sizeUnit" : "px",
                "style" : "normal",
                "weight" : "400",
                "lineHeight" : "16px"
              },
              "legendLabelColor" : "rgba(0, 0, 0, 0.76)",
              "legendValueFont" : {
                "family" : "Roboto",
                "size" : 12,
                "sizeUnit" : "px",
                "style" : "normal",
                "weight" : "500",
                "lineHeight" : "16px"
              },
              "legendValueColor" : "rgba(0, 0, 0, 0.87)",
              "legendConfig" : {
                "direction" : "column",
                "position" : "top",
                "sortDataKeys" : false,
                "showMin" : false,
                "showMax" : false,
                "showAvg" : false,
                "showTotal" : false,
                "showLatest" : true
              },
              "showTooltip" : true,
              "tooltipTrigger" : "axis",
              "tooltipLabelFont" : {
                "family" : "Roboto",
                "size" : 12,
                "sizeUnit" : "px",
                "style" : "normal",
                "weight" : "400",
                "lineHeight" : "16px"
              },
              "tooltipLabelColor" : "rgba(0, 0, 0, 0.76)",
              "tooltipValueFont" : {
                "family" : "Roboto",
                "size" : 12,
                "sizeUnit" : "px",
                "style" : "normal",
                "weight" : "500",
                "lineHeight" : "16px"
              },
              "tooltipValueColor" : "rgba(0, 0, 0, 0.76)",
              "tooltipValueFormatter" : null,
              "tooltipShowDate" : true,
              "tooltipDateFormat" : {
                "format" : null,
                "lastUpdateAgo" : false,
                "custom" : false,
                "auto" : true,
                "autoDateFormatSettings" : { }
              },
              "tooltipDateFont" : {
                "family" : "Roboto",
                "size" : 11,
                "sizeUnit" : "px",
                "style" : "normal",
                "weight" : "400",
                "lineHeight" : "16px"
              },
              "tooltipDateColor" : "rgba(0, 0, 0, 0.76)",
              "tooltipDateInterval" : true,
              "tooltipBackgroundColor" : "rgba(255, 255, 255, 0.76)",
              "tooltipBackgroundBlur" : 4,
              "animation" : {
                "animation" : true,
                "animationThreshold" : 2000,
                "animationDuration" : 500,
                "animationEasing" : "cubicOut",
                "animationDelay" : 0,
                "animationDurationUpdate" : 300,
                "animationEasingUpdate" : "cubicOut",
                "animationDelayUpdate" : 0
              },
              "background" : {
                "type" : "color",
                "color" : "#fff",
                "overlay" : {
                  "enabled" : false,
                  "color" : "rgba(255,255,255,0.72)",
                  "blur" : 3
                }
              },
              "padding" : "12px"
            },
            "title" : "Primary Current",
            "dropShadow" : true,
            "enableFullscreen" : true,
            "titleStyle" : null,
            "configMode" : "advanced",
            "actions" : { },
            "showTitleIcon" : false,
            "titleIcon" : "thermostat",
            "iconColor" : "#1F6BDD",
            "useDashboardTimewindow" : false,
            "displayTimewindow" : true,
            "titleFont" : {
              "size" : 16,
              "sizeUnit" : "px",
              "family" : "Roboto",
              "weight" : "500",
              "style" : "normal",
              "lineHeight" : "24px"
            },
            "titleColor" : "rgba(0, 0, 0, 0.87)",
            "titleTooltip" : "",
            "widgetStyle" : { },
            "widgetCss" : "",
            "pageSize" : 1024,
            "units" : "",
            "decimals" : null,
            "noDataDisplayMessage" : "",
            "timewindowStyle" : {
              "showIcon" : false,
              "iconSize" : "24px",
              "icon" : null,
              "iconPosition" : "left",
              "font" : {
                "size" : 12,
                "sizeUnit" : "px",
                "family" : "Roboto",
                "weight" : "400",
                "style" : "normal",
                "lineHeight" : "16px"
              },
              "color" : "rgba(0, 0, 0, 0.38)",
              "displayTypePrefix" : true
            },
            "margin" : "0px",
            "borderRadius" : "0px",
            "iconSize" : "0px"
          },
          "row" : 0,
          "col" : 0,
          "id" : "622ddf4b-0b7a-f19d-6f50-0d6192ace56b"
        },
        "94504aa8-43b4-ae0f-d5a1-cd8e81be701a" : {
          "typeFullFqn" : "system.cards.timeseries_table",
          "type" : "timeseries",
          "sizeX" : 8,
          "sizeY" : 6.5,
          "config" : {
            "datasources" : [ {
              "type" : "entity",
              "name" : "",
              "deviceId" : "46040460-9070-11ef-8b08-b1b78211b00c",
              "entityAliasId" : "0df20127-4849-dab6-fc9d-6201452d51f9",
              "filterId" : null,
              "dataKeys" : [ {
                "name" : "Fault1 Timestamp",
                "type" : "timeseries",
                "label" : "Fault Timestamp",
                "color" : "#8bc34a",
                "settings" : { },
                "_hash" : 0.22584523926775502,
                "aggregationType" : null,
                "units" : null,
                "decimals" : null,
                "funcBody" : null,
                "usePostProcessing" : null,
                "postFuncBody" : null
              }, {
                "name" : "Fault1 Trigger",
                "type" : "timeseries",
                "label" : "Fault Trigger",
                "color" : "#9c27b0",
                "settings" : { },
                "_hash" : 0.9081404948723353,
                "decimals" : null,
                "aggregationType" : null,
                "units" : null,
                "funcBody" : null,
                "usePostProcessing" : null,
                "postFuncBody" : null
              }, {
                "name" : "Fault1 Group",
                "type" : "timeseries",
                "label" : "Group",
                "color" : "#2196f3",
                "settings" : { },
                "_hash" : 0.5635207899300276,
                "units" : "",
                "decimals" : 0,
                "aggregationType" : null,
                "funcBody" : null,
                "usePostProcessing" : null,
                "postFuncBody" : null
              }, {
                "name" : "Fault1 R %",
                "type" : "timeseries",
                "label" : "Fault Current R (A)",
                "color" : "#ffc107",
                "settings" : { },
                "_hash" : 0.33213911577839905,
                "aggregationType" : null,
                "units" : "A",
                "decimals" : 2,
                "funcBody" : null,
                "usePostProcessing" : null,
                "postFuncBody" : null
              }, {
                "name" : "Fault1 Y %",
                "type" : "timeseries",
                "label" : "Fault Current Y (A)",
                "color" : "#607d8b",
                "settings" : { },
                "_hash" : 0.7504971330694128,
                "aggregationType" : null,
                "units" : "A",
                "decimals" : 2,
                "funcBody" : null,
                "usePostProcessing" : null,
                "postFuncBody" : null
              }, {
                "name" : "Fault1 B %",
                "type" : "timeseries",
                "label" : "Fault Current B (A)",
                "color" : "#9c27b0",
                "settings" : { },
                "_hash" : 0.39445318064153323,
                "aggregationType" : null,
                "units" : "A",
                "decimals" : 2,
                "funcBody" : null,
                "usePostProcessing" : null,
                "postFuncBody" : null
              }, {
                "name" : "Fault1 E %",
                "type" : "timeseries",
                "label" : "Fault Current E (A)",
                "color" : "#8bc34a",
                "settings" : { },
                "_hash" : 0.7938640638613499,
                "aggregationType" : null,
                "units" : "A",
                "decimals" : 2,
                "funcBody" : null,
                "usePostProcessing" : null,
                "postFuncBody" : null
              } ],
              "alarmFilterConfig" : {
                "statusList" : [ "ACTIVE" ]
              },
              "latestDataKeys" : [ ]
            } ],
            "timewindow" : {
              "hideInterval" : false,
              "hideLastInterval" : false,
              "hideQuickInterval" : false,
              "hideAggregation" : false,
              "hideAggInterval" : false,
              "hideTimezone" : false,
              "selectedTab" : 0,
              "realtime" : {
                "realtimeType" : 0,
                "timewindowMs" : 1800000,
                "quickInterval" : "CURRENT_DAY",
                "interval" : 1000
              },
              "aggregation" : {
                "type" : "NONE",
                "limit" : 200
              },
              "timezone" : null
            },
            "showTitle" : true,
            "backgroundColor" : "rgb(255, 255, 255)",
            "color" : "rgba(0, 0, 0, 0.87)",
            "padding" : "8px",
            "settings" : {
              "enableSearch" : true,
              "enableSelectColumnDisplay" : true,
              "enableStickyHeader" : true,
              "enableStickyAction" : true,
              "showCellActionsMenu" : true,
              "reserveSpaceForHiddenAction" : "true",
              "showTimestamp" : false,
              "dateFormat" : {
                "format" : "yyyy-MM-dd HH:mm:ss"
              },
              "displayPagination" : true,
              "useEntityLabel" : false,
              "defaultPageSize" : 10,
              "hideEmptyLines" : false,
              "disableStickyHeader" : false,
              "useRowStyleFunction" : false,
              "rowStyleFunction" : ""
            },
            "title" : "Fault Table",
            "dropShadow" : true,
            "enableFullscreen" : true,
            "titleStyle" : {
              "fontSize" : "16px",
              "fontWeight" : 400,
              "padding" : "5px 10px 5px 10px"
            },
            "useDashboardTimewindow" : false,
            "showLegend" : false,
            "widgetStyle" : { },
            "actions" : { },
            "showTitleIcon" : false,
            "iconColor" : "rgba(0, 0, 0, 0.87)",
            "iconSize" : "24px",
            "displayTimewindow" : true,
            "configMode" : "advanced",
            "titleFont" : null,
            "titleColor" : null,
            "titleIcon" : null,
            "titleTooltip" : "",
            "widgetCss" : "",
            "pageSize" : 1024,
            "noDataDisplayMessage" : ""
          },
          "row" : 0,
          "col" : 0,
          "id" : "94504aa8-43b4-ae0f-d5a1-cd8e81be701a"
        },
        "65f5fd0a-a849-1d35-9dd9-773763128013" : {
          "typeFullFqn" : "system.cards.html_card",
          "type" : "static",
          "sizeX" : 7.5,
          "sizeY" : 3,
          "config" : {
            "datasources" : [ {
              "type" : "static",
              "name" : "function",
              "dataKeys" : [ {
                "name" : "f(x)",
                "type" : "function",
                "label" : "Random",
                "color" : "#2196f3",
                "settings" : { },
                "_hash" : 0.15479322438769105,
                "funcBody" : "var value = prevValue + Math.random() * 100 - 50;\nvar multiplier = Math.pow(10, 2 || 0);\nvar value = Math.round(value * multiplier) / multiplier;\nif (value < -1000) {\n\tvalue = -1000;\n} else if (value > 1000) {\n\tvalue = 1000;\n}\nreturn value;"
              } ]
            } ],
            "timewindow" : {
              "realtime" : {
                "timewindowMs" : 60000
              }
            },
            "showTitle" : false,
            "backgroundColor" : "rgb(255, 255, 255)",
            "color" : "rgba(0, 0, 0, 0.87)",
            "padding" : "8px",
            "settings" : {
              "cardHtml" : "<div class='card'>Relay Monitoring Dashboard</div>",
              "cardCss" : ".card {\n    font-weight: bold;\n    font-size: 36px;\n    color: #305680;\n    width: 100%;\n    height: 100%;\n    display: flex;\n    align-items: center;\n    justify-content: center;\n}"
            },
            "title" : "HTML Card",
            "dropShadow" : true
          },
          "row" : 0,
          "col" : 0,
          "id" : "65f5fd0a-a849-1d35-9dd9-773763128013"
        },
        "d07b8e58-2352-471c-5305-12644d3eb930" : {
          "typeFullFqn" : "system.cards.html_value_card",
          "type" : "latest",
          "sizeX" : 7.5,
          "sizeY" : 3,
          "config" : {
            "datasources" : [ {
              "type" : "entity",
              "name" : "",
              "deviceId" : "f9160580-9953-11ef-8b08-b1b78211b00c",
              "entityAliasId" : "0df20127-4849-dab6-fc9d-6201452d51f9",
              "dataKeys" : [ {
                "name" : "manufacturer_name",
                "type" : "timeseries",
                "label" : "manufacturer_name",
                "color" : "#2196f3",
                "settings" : { },
                "_hash" : 0.6674480675198582
              } ],
              "alarmFilterConfig" : {
                "statusList" : [ "ACTIVE" ]
              }
            } ],
            "timewindow" : {
              "displayValue" : "",
              "selectedTab" : 0,
              "realtime" : {
                "realtimeType" : 1,
                "interval" : 1000,
                "timewindowMs" : 60000,
                "quickInterval" : "CURRENT_DAY"
              },
              "history" : {
                "historyType" : 0,
                "interval" : 1000,
                "timewindowMs" : 60000,
                "fixedTimewindow" : {
                  "startTimeMs" : 1730810497459,
                  "endTimeMs" : 1730896897459
                },
                "quickInterval" : "CURRENT_DAY"
              },
              "aggregation" : {
                "type" : "AVG",
                "limit" : 25000
              }
            },
            "showTitle" : false,
            "backgroundColor" : "#fff",
            "color" : "rgba(0, 0, 0, 0.87)",
            "padding" : "0px",
            "settings" : {
              "cardHtml" : "<center>\n    <div class='card'>\n        <div class=\"info-row\">\n            <p class=\"relay-title\">Profile: Relay</p>\n            <p class=\"manufacturer-name\">Manufacturer: Stelmec Ltd.</p>\n        </div>\n    </div>\n</center>",
              "cardCss" : "@import url('https://fonts.googleapis.com/css2?family=Orbitron:wght@500&display=swap'); /* Clean futuristic font */\n\nbody {\n    font-family: 'Times New Roman',Times New Roman;\n    background-color: #fff; /* Dark background for contrast */\n    margin: 0;\n    height: auto; /* Take full viewport height */\n    display: flex;\n    justify-content: center; /* Center horizontally */\n    align-items: center; /* Center vertically */\n}\n\n.card {\n    \n    justify-content: center; /* Center horizontally */\n    align-items: center; /* Center vertically */\n    background-color: #fff; /* Simplified dark card background */\n    color: #ffffff;\n    width: 100%;\n    height: auto; /* Adjusted height for the horizontal layout */\n    padding-left: 50px;\n    padding-right: 50px;\n    border-radius: 16px; /* Slightly more rounded corners for a modern look */\n    box-shadow: 0 15px 30px rgba(0, 0, 0, 0.3); /* Stronger shadow for depth */\n}\n\n.info-row {\n    padding-top:15px;\n    display: flex;\n    justify-content: space-between;\n    width: 100%; /* Occupy the full width of the card */\n    align-items: center; /* Align the items in the center vertically */\n    align-content: center;\n    height: 50px;\n    \n}\n\n.relay-title {\n    font-size: 22px;\n    font-weight: 600;\n    color: #305680; \n    flex: 1; /* Ensure the title takes up one-third of the width */\n    text-align: left;\n}\n\n.serial-number {\n    font-weight: 600;\n    font-size: 22px;\n    color: #305680;\n    flex: 1;\n    text-align: right; /* Center the serial number */\n}\n\n.manufacturer-name {\n    font-size: 22px;\n    color: #305680;\n    font-weight: 600;\n    flex: 1;\n    text-align: center; /* Align the manufacturer name to the right */\n}"
            },
            "title" : "HTML Value Card",
            "dropShadow" : false,
            "enableFullscreen" : true,
            "widgetStyle" : { },
            "titleStyle" : {
              "fontSize" : "16px",
              "fontWeight" : 400
            },
            "useDashboardTimewindow" : true,
            "showLegend" : false,
            "actions" : { },
            "displayTimewindow" : true
          },
          "row" : 0,
          "col" : 0,
          "id" : "d07b8e58-2352-471c-5305-12644d3eb930"
        },
        "d76b1276-b504-87f6-d945-45112eff6795" : {
          "typeFullFqn" : "system.line_chart",
          "type" : "timeseries",
          "sizeX" : 8,
          "sizeY" : 5,
          "config" : {
            "datasources" : [ {
              "type" : "entity",
              "name" : "",
              "deviceId" : "46040460-9070-11ef-8b08-b1b78211b00c",
              "entityAliasId" : "0df20127-4849-dab6-fc9d-6201452d51f9",
              "dataKeys" : [ {
                "name" : "Secondary Current R",
                "type" : "timeseries",
                "label" : "Secondary Current (r)",
                "color" : "#2196f3",
                "settings" : {
                  "yAxisId" : "default",
                  "showInLegend" : true,
                  "dataHiddenByDefault" : false,
                  "type" : "line",
                  "lineSettings" : {
                    "showLine" : true,
                    "step" : false,
                    "stepType" : "start",
                    "smooth" : false,
                    "lineType" : "solid",
                    "lineWidth" : 2,
                    "showPoints" : false,
                    "showPointLabel" : false,
                    "pointLabelPosition" : "top",
                    "pointLabelFont" : {
                      "family" : "Roboto",
                      "size" : 11,
                      "sizeUnit" : "px",
                      "style" : "normal",
                      "weight" : "400",
                      "lineHeight" : "1"
                    },
                    "pointLabelColor" : "rgba(0, 0, 0, 0.76)",
                    "enablePointLabelBackground" : false,
                    "pointLabelBackground" : "rgba(255,255,255,0.56)",
                    "pointShape" : "emptyCircle",
                    "pointSize" : 4,
                    "fillAreaSettings" : {
                      "type" : "none",
                      "opacity" : 0.4,
                      "gradient" : {
                        "start" : 100,
                        "end" : 0
                      }
                    }
                  },
                  "barSettings" : {
                    "showBorder" : false,
                    "borderWidth" : 2,
                    "borderRadius" : 0,
                    "showLabel" : false,
                    "labelPosition" : "top",
                    "labelFont" : {
                      "family" : "Roboto",
                      "size" : 11,
                      "sizeUnit" : "px",
                      "style" : "normal",
                      "weight" : "400",
                      "lineHeight" : "1"
                    },
                    "labelColor" : "rgba(0, 0, 0, 0.76)",
                    "enableLabelBackground" : false,
                    "labelBackground" : "rgba(255,255,255,0.56)",
                    "backgroundSettings" : {
                      "type" : "none",
                      "opacity" : 0.4,
                      "gradient" : {
                        "start" : 100,
                        "end" : 0
                      }
                    }
                  },
                  "comparisonSettings" : {
                    "showValuesForComparison" : false,
                    "comparisonValuesLabel" : "",
                    "color" : ""
                  }
                },
                "_hash" : 0.8800389664836736,
                "decimals" : 2,
                "units" : "A"
              }, {
                "name" : "Secondary Current Y",
                "type" : "timeseries",
                "label" : "Secondary Current (y)",
                "color" : "#4caf50",
                "settings" : {
                  "yAxisId" : "default",
                  "showInLegend" : true,
                  "dataHiddenByDefault" : false,
                  "type" : "line",
                  "lineSettings" : {
                    "showLine" : true,
                    "step" : false,
                    "stepType" : "start",
                    "smooth" : false,
                    "lineType" : "solid",
                    "lineWidth" : 2,
                    "showPoints" : false,
                    "showPointLabel" : false,
                    "pointLabelPosition" : "top",
                    "pointLabelFont" : {
                      "family" : "Roboto",
                      "size" : 11,
                      "sizeUnit" : "px",
                      "style" : "normal",
                      "weight" : "400",
                      "lineHeight" : "1"
                    },
                    "pointLabelColor" : "rgba(0, 0, 0, 0.76)",
                    "enablePointLabelBackground" : false,
                    "pointLabelBackground" : "rgba(255,255,255,0.56)",
                    "pointShape" : "emptyCircle",
                    "pointSize" : 4,
                    "fillAreaSettings" : {
                      "type" : "none",
                      "opacity" : 0.4,
                      "gradient" : {
                        "start" : 100,
                        "end" : 0
                      }
                    }
                  },
                  "barSettings" : {
                    "showBorder" : false,
                    "borderWidth" : 2,
                    "borderRadius" : 0,
                    "showLabel" : false,
                    "labelPosition" : "top",
                    "labelFont" : {
                      "family" : "Roboto",
                      "size" : 11,
                      "sizeUnit" : "px",
                      "style" : "normal",
                      "weight" : "400",
                      "lineHeight" : "1"
                    },
                    "labelColor" : "rgba(0, 0, 0, 0.76)",
                    "enableLabelBackground" : false,
                    "labelBackground" : "rgba(255,255,255,0.56)",
                    "backgroundSettings" : {
                      "type" : "none",
                      "opacity" : 0.4,
                      "gradient" : {
                        "start" : 100,
                        "end" : 0
                      }
                    }
                  },
                  "comparisonSettings" : {
                    "showValuesForComparison" : false,
                    "comparisonValuesLabel" : "",
                    "color" : ""
                  }
                },
                "_hash" : 0.49583218328359013,
                "decimals" : 2,
                "units" : "A"
              }, {
                "name" : "Secondary Current B",
                "type" : "timeseries",
                "label" : "Secondary Current (b)",
                "color" : "#f44336",
                "settings" : {
                  "yAxisId" : "default",
                  "showInLegend" : true,
                  "dataHiddenByDefault" : false,
                  "type" : "line",
                  "lineSettings" : {
                    "showLine" : true,
                    "step" : false,
                    "stepType" : "start",
                    "smooth" : false,
                    "lineType" : "solid",
                    "lineWidth" : 2,
                    "showPoints" : false,
                    "showPointLabel" : false,
                    "pointLabelPosition" : "top",
                    "pointLabelFont" : {
                      "family" : "Roboto",
                      "size" : 11,
                      "sizeUnit" : "px",
                      "style" : "normal",
                      "weight" : "400",
                      "lineHeight" : "1"
                    },
                    "pointLabelColor" : "rgba(0, 0, 0, 0.76)",
                    "enablePointLabelBackground" : false,
                    "pointLabelBackground" : "rgba(255,255,255,0.56)",
                    "pointShape" : "emptyCircle",
                    "pointSize" : 4,
                    "fillAreaSettings" : {
                      "type" : "none",
                      "opacity" : 0.4,
                      "gradient" : {
                        "start" : 100,
                        "end" : 0
                      }
                    }
                  },
                  "barSettings" : {
                    "showBorder" : false,
                    "borderWidth" : 2,
                    "borderRadius" : 0,
                    "showLabel" : false,
                    "labelPosition" : "top",
                    "labelFont" : {
                      "family" : "Roboto",
                      "size" : 11,
                      "sizeUnit" : "px",
                      "style" : "normal",
                      "weight" : "400",
                      "lineHeight" : "1"
                    },
                    "labelColor" : "rgba(0, 0, 0, 0.76)",
                    "enableLabelBackground" : false,
                    "labelBackground" : "rgba(255,255,255,0.56)",
                    "backgroundSettings" : {
                      "type" : "none",
                      "opacity" : 0.4,
                      "gradient" : {
                        "start" : 100,
                        "end" : 0
                      }
                    }
                  },
                  "comparisonSettings" : {
                    "showValuesForComparison" : false,
                    "comparisonValuesLabel" : "",
                    "color" : ""
                  }
                },
                "_hash" : 0.7548540698298956,
                "decimals" : 2,
                "units" : "A"
              }, {
                "name" : "Secondary Current E",
                "type" : "timeseries",
                "label" : "Secondary Current (e)",
                "color" : "#ffc107",
                "settings" : {
                  "yAxisId" : "default",
                  "showInLegend" : true,
                  "dataHiddenByDefault" : false,
                  "type" : "line",
                  "lineSettings" : {
                    "showLine" : true,
                    "step" : false,
                    "stepType" : "start",
                    "smooth" : false,
                    "lineType" : "solid",
                    "lineWidth" : 2,
                    "showPoints" : false,
                    "showPointLabel" : false,
                    "pointLabelPosition" : "top",
                    "pointLabelFont" : {
                      "family" : "Roboto",
                      "size" : 11,
                      "sizeUnit" : "px",
                      "style" : "normal",
                      "weight" : "400",
                      "lineHeight" : "1"
                    },
                    "pointLabelColor" : "rgba(0, 0, 0, 0.76)",
                    "enablePointLabelBackground" : false,
                    "pointLabelBackground" : "rgba(255,255,255,0.56)",
                    "pointShape" : "emptyCircle",
                    "pointSize" : 4,
                    "fillAreaSettings" : {
                      "type" : "none",
                      "opacity" : 0.4,
                      "gradient" : {
                        "start" : 100,
                        "end" : 0
                      }
                    }
                  },
                  "barSettings" : {
                    "showBorder" : false,
                    "borderWidth" : 2,
                    "borderRadius" : 0,
                    "showLabel" : false,
                    "labelPosition" : "top",
                    "labelFont" : {
                      "family" : "Roboto",
                      "size" : 11,
                      "sizeUnit" : "px",
                      "style" : "normal",
                      "weight" : "400",
                      "lineHeight" : "1"
                    },
                    "labelColor" : "rgba(0, 0, 0, 0.76)",
                    "enableLabelBackground" : false,
                    "labelBackground" : "rgba(255,255,255,0.56)",
                    "backgroundSettings" : {
                      "type" : "none",
                      "opacity" : 0.4,
                      "gradient" : {
                        "start" : 100,
                        "end" : 0
                      }
                    }
                  },
                  "comparisonSettings" : {
                    "showValuesForComparison" : false,
                    "comparisonValuesLabel" : "",
                    "color" : ""
                  }
                },
                "_hash" : 0.7727774001604235,
                "units" : "A",
                "decimals" : 2,
                "aggregationType" : null,
                "funcBody" : null,
                "usePostProcessing" : null,
                "postFuncBody" : null
              } ],
              "alarmFilterConfig" : {
                "statusList" : [ "ACTIVE" ]
              },
              "latestDataKeys" : null
            } ],
            "timewindow" : {
              "hideInterval" : false,
              "hideLastInterval" : false,
              "hideQuickInterval" : false,
              "hideAggregation" : false,
              "hideAggInterval" : false,
              "hideTimezone" : false,
              "selectedTab" : 0,
              "realtime" : {
                "realtimeType" : 0,
                "timewindowMs" : 300000,
                "quickInterval" : "CURRENT_HOUR",
                "interval" : 300000
              },
              "aggregation" : {
                "type" : "NONE",
                "limit" : 25000
              },
              "timezone" : null
            },
            "showTitle" : true,
            "backgroundColor" : "rgba(0, 0, 0, 0)",
            "color" : "rgba(0, 0, 0, 0.87)",
            "padding" : "0px",
            "settings" : {
              "comparisonEnabled" : false,
              "timeForComparison" : "previousInterval",
              "comparisonCustomIntervalValue" : 7200000,
              "comparisonXAxis" : {
                "show" : true,
                "label" : "",
                "labelFont" : {
                  "family" : "Roboto",
                  "size" : 12,
                  "sizeUnit" : "px",
                  "style" : "normal",
                  "weight" : "600",
                  "lineHeight" : "1"
                },
                "labelColor" : "rgba(0, 0, 0, 0.54)",
                "position" : "top",
                "showTickLabels" : true,
                "tickLabelFont" : {
                  "family" : "Roboto",
                  "size" : 10,
                  "sizeUnit" : "px",
                  "style" : "normal",
                  "weight" : "400",
                  "lineHeight" : "1"
                },
                "tickLabelColor" : "rgba(0, 0, 0, 0.54)",
                "ticksFormat" : { },
                "showTicks" : true,
                "ticksColor" : "rgba(0, 0, 0, 0.54)",
                "showLine" : true,
                "lineColor" : "rgba(0, 0, 0, 0.54)",
                "showSplitLines" : true,
                "splitLinesColor" : "rgba(0, 0, 0, 0.12)"
              },
              "yAxes" : {
                "default" : {
                  "units" : "A",
                  "decimals" : 2,
                  "show" : true,
                  "label" : "",
                  "labelFont" : {
                    "family" : "Roboto",
                    "size" : 12,
                    "sizeUnit" : "px",
                    "style" : "normal",
                    "weight" : "600",
                    "lineHeight" : "1"
                  },
                  "labelColor" : "rgba(0, 0, 0, 0.54)",
                  "position" : "left",
                  "showTickLabels" : true,
                  "tickLabelFont" : {
                    "family" : "Roboto",
                    "size" : 12,
                    "sizeUnit" : "px",
                    "style" : "normal",
                    "weight" : "400",
                    "lineHeight" : "1"
                  },
                  "tickLabelColor" : "rgba(0, 0, 0, 0.54)",
                  "ticksFormatter" : null,
                  "showTicks" : true,
                  "ticksColor" : "rgba(0, 0, 0, 0.54)",
                  "showLine" : true,
                  "lineColor" : "rgba(0, 0, 0, 0.54)",
                  "showSplitLines" : true,
                  "splitLinesColor" : "rgba(0, 0, 0, 0.12)",
                  "id" : "default",
                  "order" : 0,
                  "min" : 0,
                  "max" : null,
                  "ticksGenerator" : null,
                  "interval" : null,
                  "splitNumber" : null
                }
              },
              "thresholds" : [ ],
              "dataZoom" : true,
              "stack" : false,
              "grid" : {
                "show" : false,
                "backgroundColor" : null,
                "borderWidth" : 1,
                "borderColor" : "#ccc"
              },
              "xAxis" : {
                "show" : true,
                "label" : "",
                "labelFont" : {
                  "family" : "Roboto",
                  "size" : 12,
                  "sizeUnit" : "px",
                  "style" : "normal",
                  "weight" : "600",
                  "lineHeight" : "1"
                },
                "labelColor" : "rgba(0, 0, 0, 0.54)",
                "position" : "bottom",
                "showTickLabels" : true,
                "tickLabelFont" : {
                  "family" : "Roboto",
                  "size" : 10,
                  "sizeUnit" : "px",
                  "style" : "normal",
                  "weight" : "400",
                  "lineHeight" : "1"
                },
                "tickLabelColor" : "rgba(0, 0, 0, 0.54)",
                "ticksFormat" : { },
                "showTicks" : true,
                "ticksColor" : "rgba(0, 0, 0, 0.54)",
                "showLine" : true,
                "lineColor" : "rgba(0, 0, 0, 0.54)",
                "showSplitLines" : true,
                "splitLinesColor" : "rgba(0, 0, 0, 0.12)"
              },
              "noAggregationBarWidthSettings" : {
                "strategy" : "group",
                "groupWidth" : {
                  "relative" : true,
                  "relativeWidth" : 2,
                  "absoluteWidth" : 1000
                },
                "barWidth" : {
                  "relative" : true,
                  "relativeWidth" : 2,
                  "absoluteWidth" : 1000
                }
              },
              "showLegend" : true,
              "legendColumnTitleFont" : {
                "family" : "Roboto",
                "size" : 12,
                "sizeUnit" : "px",
                "style" : "normal",
                "weight" : "400",
                "lineHeight" : "16px"
              },
              "legendColumnTitleColor" : "rgba(0, 0, 0, 0.38)",
              "legendLabelFont" : {
                "family" : "Roboto",
                "size" : 12,
                "sizeUnit" : "px",
                "style" : "normal",
                "weight" : "400",
                "lineHeight" : "16px"
              },
              "legendLabelColor" : "rgba(0, 0, 0, 0.76)",
              "legendValueFont" : {
                "family" : "Roboto",
                "size" : 12,
                "sizeUnit" : "px",
                "style" : "normal",
                "weight" : "500",
                "lineHeight" : "16px"
              },
              "legendValueColor" : "rgba(0, 0, 0, 0.87)",
              "legendConfig" : {
                "direction" : "column",
                "position" : "top",
                "sortDataKeys" : false,
                "showMin" : false,
                "showMax" : false,
                "showAvg" : false,
                "showTotal" : false,
                "showLatest" : true
              },
              "showTooltip" : true,
              "tooltipTrigger" : "axis",
              "tooltipLabelFont" : {
                "family" : "Roboto",
                "size" : 12,
                "sizeUnit" : "px",
                "style" : "normal",
                "weight" : "400",
                "lineHeight" : "16px"
              },
              "tooltipLabelColor" : "rgba(0, 0, 0, 0.76)",
              "tooltipValueFont" : {
                "family" : "Roboto",
                "size" : 12,
                "sizeUnit" : "px",
                "style" : "normal",
                "weight" : "500",
                "lineHeight" : "16px"
              },
              "tooltipValueColor" : "rgba(0, 0, 0, 0.76)",
              "tooltipValueFormatter" : null,
              "tooltipShowDate" : true,
              "tooltipDateFormat" : {
                "format" : null,
                "lastUpdateAgo" : false,
                "custom" : false,
                "auto" : true,
                "autoDateFormatSettings" : { }
              },
              "tooltipDateFont" : {
                "family" : "Roboto",
                "size" : 11,
                "sizeUnit" : "px",
                "style" : "normal",
                "weight" : "400",
                "lineHeight" : "16px"
              },
              "tooltipDateColor" : "rgba(0, 0, 0, 0.76)",
              "tooltipDateInterval" : true,
              "tooltipBackgroundColor" : "rgba(255, 255, 255, 0.76)",
              "tooltipBackgroundBlur" : 4,
              "animation" : {
                "animation" : true,
                "animationThreshold" : 2000,
                "animationDuration" : 500,
                "animationEasing" : "cubicOut",
                "animationDelay" : 0,
                "animationDurationUpdate" : 300,
                "animationEasingUpdate" : "cubicOut",
                "animationDelayUpdate" : 0
              },
              "background" : {
                "type" : "color",
                "color" : "#fff",
                "overlay" : {
                  "enabled" : false,
                  "color" : "rgba(255,255,255,0.72)",
                  "blur" : 3
                }
              },
              "padding" : "12px"
            },
            "title" : "Secondary Current",
            "dropShadow" : true,
            "enableFullscreen" : true,
            "titleStyle" : null,
            "configMode" : "advanced",
            "actions" : { },
            "showTitleIcon" : false,
            "titleIcon" : "thermostat",
            "iconColor" : "#1F6BDD",
            "useDashboardTimewindow" : false,
            "displayTimewindow" : true,
            "titleFont" : {
              "size" : 16,
              "sizeUnit" : "px",
              "family" : "Roboto",
              "weight" : "500",
              "style" : "normal",
              "lineHeight" : "24px"
            },
            "titleColor" : "rgba(0, 0, 0, 0.87)",
            "titleTooltip" : "",
            "widgetStyle" : { },
            "widgetCss" : "",
            "pageSize" : 1024,
            "units" : "",
            "decimals" : null,
            "noDataDisplayMessage" : "",
            "timewindowStyle" : {
              "showIcon" : false,
              "iconSize" : "24px",
              "icon" : null,
              "iconPosition" : "left",
              "font" : {
                "size" : 12,
                "sizeUnit" : "px",
                "family" : "Roboto",
                "weight" : "400",
                "style" : "normal",
                "lineHeight" : "16px"
              },
              "color" : "rgba(0, 0, 0, 0.38)",
              "displayTypePrefix" : true
            },
            "margin" : "0px",
            "borderRadius" : "0px",
            "iconSize" : "0px"
          },
          "row" : 0,
          "col" : 0,
          "id" : "d76b1276-b504-87f6-d945-45112eff6795"
        },
        "8507eecd-2afa-d48a-5adb-f31c445ef23b" : {
          "typeFullFqn" : "system.cards.html_value_card",
          "type" : "latest",
          "sizeX" : 7.5,
          "sizeY" : 3,
          "config" : {
            "datasources" : [ {
              "type" : "entity",
              "name" : "",
              "deviceId" : "469c25b0-9070-11ef-8b08-b1b78211b00c",
              "entityAliasId" : "0df20127-4849-dab6-fc9d-6201452d51f9",
              "dataKeys" : [ {
                "name" : "Fault1 Trigger",
                "type" : "timeseries",
                "label" : "Fault1 Trigger",
                "color" : "#9c27b0",
                "settings" : { },
                "_hash" : 0.6552079135570146,
                "aggregationType" : "NONE",
                "units" : null,
                "decimals" : null,
                "funcBody" : null,
                "usePostProcessing" : null,
                "postFuncBody" : null
              }, {
                "name" : "Fault1 Date",
                "type" : "timeseries",
                "label" : "Fault1 Date",
                "color" : "#9c27b0",
                "settings" : { },
                "_hash" : 0.6452167162739944
              }, {
                "name" : "Fault1 Time",
                "type" : "timeseries",
                "label" : "Fault1 Time",
                "color" : "#8bc34a",
                "settings" : { },
                "_hash" : 0.22125062836249576
              }, {
                "name" : "Fault1 R %",
                "type" : "timeseries",
                "label" : "Fault1 R %",
                "color" : "#ffc107",
                "settings" : { },
                "_hash" : 0.6509528460699903,
                "aggregationType" : "NONE",
                "units" : null,
                "decimals" : null,
                "funcBody" : null,
                "usePostProcessing" : true,
                "postFuncBody" : "return value.toString().padStart(4, '0');"
              }, {
                "name" : "Fault1 Y %",
                "type" : "timeseries",
                "label" : "Fault1 Y %",
                "color" : "#607d8b",
                "settings" : { },
                "_hash" : 0.1787348667160542,
                "aggregationType" : "NONE",
                "units" : null,
                "decimals" : null,
                "funcBody" : null,
                "usePostProcessing" : true,
                "postFuncBody" : "return value.toString().padStart(4, '0');"
              }, {
                "name" : "Fault1 B %",
                "type" : "timeseries",
                "label" : "Fault1 B %",
                "color" : "#9c27b0",
                "settings" : { },
                "_hash" : 0.42081595033527375,
                "aggregationType" : "NONE",
                "units" : null,
                "decimals" : null,
                "funcBody" : null,
                "usePostProcessing" : true,
                "postFuncBody" : "return value.toString().padStart(4, '0');"
              }, {
                "name" : "Fault1 E %",
                "type" : "timeseries",
                "label" : "Fault1 E %",
                "color" : "#8bc34a",
                "settings" : { },
                "_hash" : 0.4684419862769158,
                "aggregationType" : "NONE",
                "units" : null,
                "decimals" : null,
                "funcBody" : null,
                "usePostProcessing" : true,
                "postFuncBody" : "return value.toString().padStart(4, '0');"
              } ],
              "alarmFilterConfig" : {
                "statusList" : [ "ACTIVE" ]
              }
            } ],
            "timewindow" : {
              "displayValue" : "",
              "selectedTab" : 0,
              "realtime" : {
                "realtimeType" : 1,
                "interval" : 1000,
                "timewindowMs" : 60000,
                "quickInterval" : "CURRENT_DAY"
              },
              "history" : {
                "historyType" : 0,
                "interval" : 1000,
                "timewindowMs" : 60000,
                "fixedTimewindow" : {
                  "startTimeMs" : 1730810497459,
                  "endTimeMs" : 1730896897459
                },
                "quickInterval" : "CURRENT_DAY"
              },
              "aggregation" : {
                "type" : "AVG",
                "limit" : 25000
              }
            },
            "showTitle" : false,
            "backgroundColor" : "#fff",
            "color" : "rgba(0, 0, 0, 0.87)",
            "padding" : "0px",
            "settings" : {
              "cardHtml" : "<center>\n    <div class=\"card\">\n        <h6><u><b>Fault Data</b></u></h6>\n        <div class=\"trip-condition\">\n            <p><strong>Trip Condition:</strong> ${Fault1 Trigger}</p>\n        </div>\n        <div class=\"info-grid\">\n            <div class=\"info-item\">\n                <p><strong>R:</strong> ${Fault1 R %} A</p>\n            </div>\n            <div class=\"info-item\">\n                <p><strong>Y:</strong> ${Fault1 Y %} A</p>\n            </div>\n            <div class=\"info-item\">\n                <p><strong>B:</strong> ${Fault1 B %} A</p>\n            </div>\n            <div class=\"info-item\">\n                <p><strong>E:</strong> ${Fault1 E %} A</p>\n            </div>\n        </div>\n        <br>\n        <div class=\"time-date-row\">\n            <p><strong>Fault Time:</strong> ${Fault1 Time}</p>\n            <p><strong>Fault Date:</strong> ${Fault1 Date}</p>\n        </div>\n    </div>\n</center>",
              "cardCss" : "html, body {\n    margin: 0;\n    padding: 0;\n    height: 100%;\n}\n\n/* Card container inside the widget */\n.card {\n    display: flex;\n    flex-direction: column;\n    justify-content: center;\n    align-items: center;\n    background-color: #fff;\n    width: 100%;\n    padding: 0px;\n    box-sizing: border-box;\n    overflow: auto;\n    margin: 0px;\n}\n\n/* Centered trip condition */\n.trip-condition {\n    text-align: center;\n    height: 75px;\n}\n\n/* Grid format for R, Y, B, E phases */\n.info-grid {\n    display: grid;\n    grid-template-columns: repeat(2, 1fr); /* Two columns per row */\n    column-gap: 5px;  /* Slight horizontal space between items */\n    width: 100%;\n    text-align: center;\n    padding: 0;\n    margin: 0;\n}\n\n.info-item {\n    padding: 0px;\n    margin: 0px;\n    font-size: 10px;\n}\n\n.info-item p{\n    padding: 0px;\n    margin: 0px;\n}\n\n/* Centered time and date */\n.time-date-row {\n    display: flex;\n    flex-direction: column;\n    justify-content: center;\n    align-items: center;\n    width: 100%;\n    padding: 0px;\n    margin: 0px;\n}\n\n.time-date-row p{\n    margin: 0px;\n    font-size: 25px;\n}"
            },
            "title" : "HTML Value Card",
            "dropShadow" : false,
            "enableFullscreen" : true,
            "widgetStyle" : { },
            "titleStyle" : {
              "fontSize" : "16px",
              "fontWeight" : 400
            },
            "useDashboardTimewindow" : true,
            "showLegend" : false,
            "actions" : { },
            "displayTimewindow" : true
          },
          "row" : 0,
          "col" : 0,
          "id" : "8507eecd-2afa-d48a-5adb-f31c445ef23b"
        },
        "4851a4a1-1314-442e-77d1-e81cd9d30b91" : {
          "typeFullFqn" : "system.cards.html_card",
          "type" : "static",
          "sizeX" : 7.5,
          "sizeY" : 3,
          "config" : {
            "datasources" : [ {
              "type" : "static",
              "name" : "function",
              "dataKeys" : [ {
                "name" : "f(x)",
                "type" : "function",
                "label" : "Random",
                "color" : "#2196f3",
                "settings" : { },
                "_hash" : 0.15479322438769105,
                "funcBody" : "var value = prevValue + Math.random() * 100 - 50;\nvar multiplier = Math.pow(10, 2 || 0);\nvar value = Math.round(value * multiplier) / multiplier;\nif (value < -1000) {\n\tvalue = -1000;\n} else if (value > 1000) {\n\tvalue = 1000;\n}\nreturn value;"
              } ]
            } ],
            "timewindow" : {
              "realtime" : {
                "timewindowMs" : 60000
              }
            },
            "showTitle" : false,
            "backgroundColor" : "rgb(255, 255, 255)",
            "color" : "rgba(0, 0, 0, 0.87)",
            "padding" : "8px",
            "settings" : {
              "cardHtml" : "<div class=\"image-container\">\r\n    <img src=\"https://stelmec.com/wp-content/uploads/2023/02/Stelmec-WHITE-LOGO-01-2.svg\" alt=\"Stelmec Logo\">\r\n</div>",
              "cardCss" : "html, body {\n    width: 100%;\n    height: 100%;\n    margin: 0;\n}\n\nbody {\n    display: flex;\n    justify-content: center;\n    align-items: center;\n    background-color: #f5f5f5;\n}\n\n.image-container {\n    width: 100%;\n    height: 100%;\n    background: #305680;\n    display: flex;\n    justify-content: center;\n    align-items: center;\n}\n\nimg {\n    width: 100%;\n    height: 100%;\n    object-fit: contain;\n    /* Maintains aspect ratio without clipping */\n}"
            },
            "title" : "HTML Card",
            "dropShadow" : true
          },
          "row" : 0,
          "col" : 0,
          "id" : "4851a4a1-1314-442e-77d1-e81cd9d30b91"
        },
        "98ea6f9e-b3af-4d9d-def7-d8a03df78a75" : {
          "typeFullFqn" : "system.alarm_widgets.alarms_table",
          "type" : "alarm",
          "sizeX" : 10.5,
          "sizeY" : 6.5,
          "config" : {
            "timewindow" : {
              "hideInterval" : false,
              "hideLastInterval" : false,
              "hideQuickInterval" : false,
              "hideAggregation" : false,
              "hideAggInterval" : false,
              "hideTimezone" : false,
              "selectedTab" : 0,
              "realtime" : {
                "realtimeType" : 0,
                "timewindowMs" : 1800000,
                "quickInterval" : "CURRENT_DAY",
                "interval" : 1000
              },
              "aggregation" : {
                "type" : "NONE",
                "limit" : 200
              },
              "timezone" : null
            },
            "showTitle" : true,
            "backgroundColor" : "rgb(255, 255, 255)",
            "color" : "rgba(0, 0, 0, 0.87)",
            "padding" : "4px",
            "settings" : {
              "enableSelection" : true,
              "enableSearch" : true,
              "displayDetails" : true,
              "allowAcknowledgment" : true,
              "allowClear" : true,
              "allowAssign" : true,
              "displayActivity" : true,
              "displayPagination" : true,
              "defaultPageSize" : 10,
              "defaultSortOrder" : "-createdTime",
              "enableSelectColumnDisplay" : true,
              "enableStickyAction" : false,
              "enableFilter" : true,
              "entitiesTitle" : null,
              "alarmsTitle" : "Alarms"
            },
            "title" : "Alarms table",
            "dropShadow" : true,
            "enableFullscreen" : true,
            "titleStyle" : {
              "fontSize" : "16px",
              "fontWeight" : 400,
              "padding" : "5px 10px 5px 10px"
            },
            "useDashboardTimewindow" : false,
            "showLegend" : false,
            "alarmSource" : {
              "type" : "entity",
              "name" : "",
              "entityAliasId" : "0df20127-4849-dab6-fc9d-6201452d51f9",
              "dataKeys" : [ {
                "name" : "faultTs",
                "type" : "alarm",
                "label" : "Fault Timestamp",
                "color" : "#9c27b0",
                "settings" : { },
                "_hash" : 0.14049177632499932,
                "aggregationType" : null,
                "units" : null,
                "decimals" : null,
                "funcBody" : null,
                "usePostProcessing" : null,
                "postFuncBody" : null
              }, {
                "name" : "originator",
                "type" : "alarm",
                "label" : "Originator",
                "color" : "#4caf50",
                "settings" : {
                  "useCellStyleFunction" : false,
                  "cellStyleFunction" : "",
                  "useCellContentFunction" : false,
                  "cellContentFunction" : ""
                },
                "_hash" : 0.2780007688856758,
                "funcBody" : null
              }, {
                "name" : "type",
                "type" : "alarm",
                "label" : "Type",
                "color" : "#f44336",
                "settings" : {
                  "useCellStyleFunction" : false,
                  "cellStyleFunction" : "",
                  "useCellContentFunction" : false,
                  "cellContentFunction" : ""
                },
                "_hash" : 0.7323586880398418,
                "funcBody" : null
              }, {
                "name" : "status",
                "type" : "alarm",
                "label" : "Status",
                "color" : "#607d8b",
                "settings" : { },
                "_hash" : 0.42682626779710753,
                "decimals" : 0
              }, {
                "name" : "clearTime",
                "type" : "alarm",
                "label" : "Cleared time",
                "color" : "#ffc107",
                "settings" : { },
                "_hash" : 0.8784847905610009,
                "decimals" : 0
              } ],
              "alarmFilterConfig" : {
                "statusList" : [ "ACTIVE" ]
              }
            },
            "alarmsPollingInterval" : 5,
            "showTitleIcon" : false,
            "titleIcon" : "warning",
            "iconColor" : "rgba(0, 0, 0, 0.87)",
            "iconSize" : "24px",
            "titleTooltip" : "",
            "widgetStyle" : { },
            "displayTimewindow" : true,
            "actions" : { },
            "configMode" : "advanced",
            "alarmFilterConfig" : {
              "statusList" : [ "ACTIVE", "CLEARED", "ACK", "UNACK" ],
              "severityList" : [ "CRITICAL", "MAJOR", "MINOR", "WARNING", "INDETERMINATE" ],
              "typeList" : [ ],
              "searchPropagatedAlarms" : false,
              "assignedToCurrentUser" : false,
              "assigneeId" : null
            },
            "datasources" : [ ],
            "titleFont" : null,
            "titleColor" : null
          },
          "row" : 0,
          "col" : 0,
          "id" : "98ea6f9e-b3af-4d9d-def7-d8a03df78a75"
        },
        "eb3316fd-387a-4a15-f0bb-1f2eea0577f6" : {
          "typeFullFqn" : "system.control_widgets.led_indicator",
          "type" : "rpc",
          "sizeX" : 2.5,
          "sizeY" : 2.5,
          "config" : {
            "targetDeviceAliases" : [ ],
            "showTitle" : false,
            "backgroundColor" : "#e6e7e8",
            "color" : "rgba(0, 0, 0, 0.87)",
            "padding" : "0px",
            "settings" : {
              "title" : "Circuit Breaker On",
              "ledColor" : "#008F06",
              "initialValue" : false,
              "performCheckStatus" : false,
              "retrieveValueMethod" : "timeseries",
              "checkStatusMethod" : "checkStatus",
              "valueAttribute" : "Circuit Breaker",
              "parseValueFunction" : "return !data;",
              "requestTimeout" : 500,
              "requestPersistent" : false,
              "persistentPollingInterval" : 5000
            },
            "title" : "Circuit Breaker On",
            "dropShadow" : true,
            "enableFullscreen" : false,
            "widgetStyle" : { },
            "titleStyle" : {
              "display" : "flex",
              "justifyContent" : "center",
              "alignItems" : "center",
              "width" : "100%"
            },
            "useDashboardTimewindow" : true,
            "showLegend" : false,
            "actions" : { },
            "decimals" : 2,
            "datasources" : [ ],
            "targetDevice" : {
              "type" : "entity",
              "entityAliasId" : "0df20127-4849-dab6-fc9d-6201452d51f9"
            },
            "showTitleIcon" : false,
            "titleTooltip" : "",
            "widgetCss" : "",
            "pageSize" : 1024,
            "noDataDisplayMessage" : "",
            "titleIcon" : "",
            "iconColor" : "rgba(0, 0, 0, 0.87)",
            "iconSize" : "24px",
            "titleFont" : {
              "sizeUnit" : "px",
              "family" : null,
              "weight" : "bold",
              "style" : null
            }
          },
          "row" : 0,
          "col" : 0,
          "id" : "eb3316fd-387a-4a15-f0bb-1f2eea0577f6"
        },
        "dd1724a5-0ff5-0b13-64b5-1cdadce1e90d" : {
          "typeFullFqn" : "system.control_widgets.led_indicator",
          "type" : "rpc",
          "sizeX" : 2.5,
          "sizeY" : 2.5,
          "config" : {
            "targetDeviceAliases" : [ ],
            "showTitle" : false,
            "backgroundColor" : "#e6e7e8",
            "color" : "rgba(0, 0, 0, 0.87)",
            "padding" : "0px",
            "settings" : {
              "title" : " Circuit Breaker Off",
              "ledColor" : "#FF0000",
              "initialValue" : false,
              "performCheckStatus" : false,
              "retrieveValueMethod" : "timeseries",
              "checkStatusMethod" : "checkStatus",
              "valueAttribute" : "Circuit Breaker",
              "parseValueFunction" : "return data;",
              "requestTimeout" : 500,
              "requestPersistent" : false,
              "persistentPollingInterval" : 5000
            },
            "title" : "Circuit Breaker Off",
            "dropShadow" : true,
            "enableFullscreen" : false,
            "widgetStyle" : { },
            "titleStyle" : {
              "display" : "flex",
              "fontSize" : "16px",
              "fontWeight" : 400,
              "justify-content" : "center"
            },
            "useDashboardTimewindow" : true,
            "showLegend" : false,
            "actions" : { },
            "decimals" : 2,
            "datasources" : [ ],
            "targetDevice" : {
              "type" : "entity",
              "entityAliasId" : "0df20127-4849-dab6-fc9d-6201452d51f9"
            },
            "showTitleIcon" : false,
            "titleTooltip" : "",
            "widgetCss" : "",
            "pageSize" : 1024,
            "noDataDisplayMessage" : "",
            "titleIcon" : "",
            "iconColor" : "rgba(0, 0, 0, 0.87)",
            "iconSize" : "24px",
            "titleFont" : {
              "sizeUnit" : "px",
              "family" : null,
              "weight" : "bold",
              "style" : null
            }
          },
          "row" : 0,
          "col" : 0,
          "id" : "dd1724a5-0ff5-0b13-64b5-1cdadce1e90d"
        }
      },
      "states" : {
        "default" : {
          "name" : "Relay Dashboard",
          "root" : true,
          "layouts" : {
            "main" : {
              "widgets" : {
                "622ddf4b-0b7a-f19d-6f50-0d6192ace56b" : {
                  "sizeX" : 11,
                  "sizeY" : 14,
                  "row" : 5,
                  "col" : 0
                },
                "94504aa8-43b4-ae0f-d5a1-cd8e81be701a" : {
                  "sizeX" : 34,
                  "sizeY" : 12,
                  "row" : 19,
                  "col" : 0
                },
                "65f5fd0a-a849-1d35-9dd9-773763128013" : {
                  "sizeX" : 26,
                  "sizeY" : 3,
                  "row" : 0,
                  "col" : 0
                },
                "d07b8e58-2352-471c-5305-12644d3eb930" : {
                  "sizeX" : 22,
                  "sizeY" : 2,
                  "row" : 3,
                  "col" : 0
                },
                "d76b1276-b504-87f6-d945-45112eff6795" : {
                  "sizeX" : 11,
                  "sizeY" : 14,
                  "row" : 5,
                  "col" : 11
                },
                "8507eecd-2afa-d48a-5adb-f31c445ef23b" : {
                  "sizeX" : 12,
                  "sizeY" : 12,
                  "row" : 7,
                  "col" : 22
                },
                "4851a4a1-1314-442e-77d1-e81cd9d30b91" : {
                  "sizeX" : 8,
                  "sizeY" : 3,
                  "row" : 0,
                  "col" : 26
                },
                "98ea6f9e-b3af-4d9d-def7-d8a03df78a75" : {
                  "sizeX" : 34,
                  "sizeY" : 11,
                  "row" : 31,
                  "col" : 0
                },
                "eb3316fd-387a-4a15-f0bb-1f2eea0577f6" : {
                  "sizeX" : 6,
                  "sizeY" : 4,
                  "row" : 3,
                  "col" : 22
                },
                "dd1724a5-0ff5-0b13-64b5-1cdadce1e90d" : {
                  "sizeX" : 6,
                  "sizeY" : 4,
                  "row" : 3,
                  "col" : 28
                }
              },
              "gridSettings" : {
                "backgroundColor" : "#eeeeee",
                "columns" : 24,
                "margin" : 10,
                "outerMargin" : true,
                "backgroundSizeMode" : "100%"
              }
            }
          }
        }
      },
      "entityAliases" : {
        "0df20127-4849-dab6-fc9d-6201452d51f9" : {
          "id" : "0df20127-4849-dab6-fc9d-6201452d51f9",
          "alias" : "RelaySLR140",
          "filter" : {
            "type" : "singleEntity",
            "resolveMultiple" : false,
            "singleEntity" : {
              "entityType" : "DEVICE",
              "id" : "f28bf7d0-e794-11ef-8b08-b1b78211b00c"
            }
          }
        },
        "5b88916d-3962-24ec-8215-de2306a46fe6" : {
          "id" : "5b88916d-3962-24ec-8215-de2306a46fe6",
          "alias" : "RelaySLR140C",
          "filter" : {
            "type" : "singleEntity",
            "resolveMultiple" : false,
            "singleEntity" : {
              "entityType" : "DEVICE",
              "id" : "f3241920-e794-11ef-8b08-b1b78211b00c"
            }
          }
        }
      },
      "filters" : { },
      "timewindow" : {
        "hideInterval" : false,
        "hideLastInterval" : false,
        "hideQuickInterval" : false,
        "hideAggregation" : false,
        "hideAggInterval" : false,
        "hideTimezone" : false,
        "selectedTab" : 0,
        "realtime" : {
          "realtimeType" : 0,
          "timewindowMs" : 1000,
          "quickInterval" : "CURRENT_DAY",
          "interval" : 1000
        },
        "aggregation" : {
          "type" : "NONE",
          "limit" : 25000
        },
        "timezone" : null
      },
      "settings" : {
        "stateControllerId" : "entity",
        "showTitle" : false,
        "showDashboardsSelect" : true,
        "showEntitiesSelect" : true,
        "showDashboardTimewindow" : true,
        "showDashboardExport" : true,
        "toolbarAlwaysOpen" : true
      }
    },
    "externalId" : {
      "entityType" : "DASHBOARD",
      "id" : "5298b710-e945-11ef-8b08-b1b78211b00c"
    },
    "id" : {
      "entityType" : "DASHBOARD",
      "id" : "5298b710-e945-11ef-8b08-b1b78211b00c"
    },
    "image" : null,
    "mobileHide" : false,
    "mobileOrder" : null,
    "name" : "(Meshnet) Relay_SLR140_Dashboard",
    "title" : "(Meshnet) Relay_SLR140_Dashboard"
  },
  "relations" : [ ],
  "attributes" : {
    "SERVER_SCOPE" : [ ]
  }
}